sopel_pets/__init__.py
sopel_pets-1.0.0.dist-info/licenses/LICENSE
sopel_pets-1.0.0.dist-info/METADATA
sopel_pets-1.0.0.dist-info/WHEEL
sopel_pets-1.0.0.dist-info/entry_points.txt
sopel_pets-1.0.0.dist-info/top_level.txt
sopel_pets-1.0.0.dist-info/RECORD
